{
    "characterCardDatas": [
        {
            "id": 101,
            "name": "어설픈 방패병",
            "tier": 3,
            "cost": 2,
            "hp": 4,
            "mp": 1,
            "race": 0,
            "job": 1,
            "skills": [
                1000,
                3001
            ]
        },
        {
            "id": 102,
            "name": "최전선의 창병",
            "tier": 3,
            "cost": 2,
            "hp": 3,
            "mp": 1,
            "race": 0,
            "job": 1,
            "skills": [
                1000,
                2001,
                3002
            ]
        },
        {
            "id": 103,
            "name": "그림자 속 수호자",
            "tier": 3,
            "cost": 2,
            "hp": 2,
            "mp": 2,
            "race": 0,
            "job": 1,
            "skills": [
                1000,
                3003,
                3004
            ]
        },
        {
            "id": 104,
            "name": "침착한 수비수",
            "tier": 2,
            "cost": 3,
            "hp": 4,
            "mp": 2,
            "race": 0,
            "job": 1,
            "skills": [
                1000,
                3005,
                2002
            ]
        },
        {
            "id": 105,
            "name": "나태한 문지기",
            "tier": 2,
            "cost": 3,
            "hp": 2,
            "mp": 3,
            "race": 0,
            "job": 1,
            "skills": [
                1000,
                3006
            ]
        },
        {
            "id": 106,
            "name": "마법방패를 두른 수호자",
            "tier": 2,
            "cost": 3,
            "hp": 2,
            "mp": 4,
            "race": 0,
            "job": 1,
            "skills": [
                1000,
                4001,
                3007
            ]
        },
        {
            "id": 107,
            "name": "산군 -강수-",
            "tier": 1,
            "cost": 4,
            "hp": 6,
            "mp": 3,
            "race": 0,
            "job": 1,
            "skills": [
                1000,
                3008,
                2003,
                3009
            ]
        },
        {
            "id": 108,
            "name": "은결의 마녀 -루안-",
            "tier": 1,
            "cost": 4,
            "hp": 2,
            "mp": 6,
            "race": 0,
            "job": 1,
            "skills": [
                1000,
                5001,
                5002,
                3010,
                3011
            ]
        },
        {
            "id": 109,
            "name": "블러드가드 -로간-",
            "tier": 1,
            "cost": 4,
            "hp": 6,
            "mp": 3,
            "race": 0,
            "job": 1,
            "skills": [
                1000,
                4002,
                2004,
                3012,
                4003
            ]
        },
        {
            "id": 110,
            "name": "검은 장미 -엘-",
            "tier": 0,
            "cost": 0,
            "hp": 2,
            "mp": 1,
            "race": 0,
            "job": 1,
            "skills": [
                1000,
                3013
            ]
        },
        {
            "id": 111,
            "name": "빛의 방패 -세노티-",
            "tier": 0,
            "cost": 0,
            "hp": 2,
            "mp": 1,
            "race": 0,
            "job": 1,
            "skills": [
                1000,
                4004,
                4005
            ]
        },
        {
            "id": 112,
            "name": "철의 성벽 -우르-",
            "tier": 0,
            "cost": 1,
            "hp": 3,
            "mp": 1,
            "race": 0,
            "job": 1,
            "skills": [
                1000,
                3014
            ]
        },
        {
            "id": 113,
            "name": "하얀검사",
            "tier": 3,
            "cost": 2,
            "hp": 3,
            "mp": 2,
            "race": 0,
            "job": 0,
            "skills": [
                1000,
                2005
            ]
        },
        {
            "id": 114,
            "name": "그림자 속 암살자",
            "tier": 3,
            "cost": 2,
            "hp": 2,
            "mp": 2,
            "race": 0,
            "job": 0,
            "skills": [
                1000,
                2006,
                2007
            ]
        },
        {
            "id": 115,
            "name": "죽음과 함께 걷는 암살자",
            "tier": 3,
            "cost": 2,
            "hp": 2,
            "mp": 3,
            "race": 0,
            "job": 0,
            "skills": [
                1000,
                2008
            ]
        },
        {
            "id": 116,
            "name": "섬광의 명궁",
            "tier": 2,
            "cost": 3,
            "hp": 4,
            "mp": 2,
            "race": 0,
            "job": 0,
            "skills": [
                1000,
                2009,
                2010
            ]
        },
        {
            "id": 117,
            "name": "푸른눈의 저격수",
            "tier": 2,
            "cost": 3,
            "hp": 2,
            "mp": 3,
            "race": 0,
            "job": 0,
            "skills": [
                1000,
                4005,
                1001,
                2011,
                4006
            ]
        },
        {
            "id": 118,
            "name": "석양의 보안관",
            "tier": 2,
            "cost": 3,
            "hp": 3,
            "mp": 2,
            "race": 0,
            "job": 0,
            "skills": [
                1000,
                2012,
                2013,
                2014
            ]
        },
        {
            "id": 119,
            "name": "카이른 블레이즈",
            "tier": 1,
            "cost": 4,
            "hp": 6,
            "mp": 3,
            "race": 0,
            "job": 0,
            "skills": [
                1000,
                2015,
                2016,
                2017
            ]
        },
        {
            "id": 120,
            "name": "광전사 -가르칸-",
            "tier": 1,
            "cost": 4,
            "hp": 9,
            "mp": 0,
            "race": 0,
            "job": 0,
            "skills": [
                1000,
                2018,
                2019,
                2020
            ]
        },
        {
            "id": 121,
            "name": "광무 -잔영-",
            "tier": 1,
            "cost": 4,
            "hp": 5,
            "mp": 4,
            "race": 0,
            "job": 0,
            "skills": [
                1000,
                2022,
                2023,
                2024
            ]
        },
        {
            "id": 122,
            "name": "검은불꽃 -청현-",
            "tier": 0,
            "cost": 1,
            "hp": 2,
            "mp": 1,
            "race": 0,
            "job": 0,
            "skills": [
                1000,
                2025,
                2026
            ]
        },
        {
            "id": 123,
            "name": "이계의 창 -라이트-",
            "tier": 0,
            "cost": 0,
            "hp": 2,
            "mp": 1,
            "race": 0,
            "job": 0,
            "skills": [
                1000,
                2027
            ]
        },
        {
            "id": 124,
            "name": "기사단장 -자스안-",
            "tier": 0,
            "cost": 0,
            "hp": 2,
            "mp": 1,
            "race": 0,
            "job": 0,
            "skills": [
                1000,
                2028
            ]
        },
        {
            "id": 125,
            "name": "자유의 치유사",
            "tier": 3,
            "cost": 2,
            "hp": 1,
            "mp": 4,
            "race": 0,
            "job": 2,
            "skills": [
                1000,
                4007
            ]
        },
        {
            "id": 126,
            "name": "행운의 치료사",
            "tier": 3,
            "cost": 2,
            "hp": 2,
            "mp": 3,
            "race": 0,
            "job": 2,
            "skills": [
                1000,
                4008
            ]
        },
        {
            "id": 127,
            "name": "검은 마력의 저주사",
            "tier": 3,
            "cost": 2,
            "hp": 2,
            "mp": 2,
            "race": 0,
            "job": 2,
            "skills": [
                1000,
                5003,
                5004
            ]
        },
        {
            "id": 128,
            "name": "노련한 전략가",
            "tier": 2,
            "cost": 3,
            "hp": 2,
            "mp": 3,
            "race": 0,
            "job": 2,
            "skills": [
                1000,
                1002,
                4009,
                3015,
                4010
            ]
        },
        {
            "id": 129,
            "name": "교활한 정보원",
            "tier": 2,
            "cost": 3,
            "hp": 1,
            "mp": 3,
            "race": 0,
            "job": 2,
            "skills": [
                1000,
                4011,
                1003
            ]
        },
        {
            "id": 130,
            "name": "현자의 돌을 지닌 연금술사",
            "tier": 2,
            "cost": 3,
            "hp": 2,
            "mp": 4,
            "race": 0,
            "job": 2,
            "skills": [
                1000,
                4012,
                3016
            ]
        },
        {
            "id": 131,
            "name": "로열 에이드",
            "tier": 1,
            "cost": 4,
            "hp": 3,
            "mp": 5,
            "race": 0,
            "job": 2,
            "skills": [
                1000,
                4013,
                5005,
                4014,
                4015
            ]
        },
        {
            "id": 132,
            "name": "북방의 마법현자 -와이즈-",
            "tier": 1,
            "cost": 4,
            "hp": 5,
            "mp": 4,
            "race": 0,
            "job": 2,
            "skills": [
                1000,
                4016,
                4017,
                5006,
                4018,
                4019
            ]
        },
        {
            "id": 133,
            "name": "순풍의 가인 -라에나-",
            "tier": 1,
            "cost": 4,
            "hp": 3,
            "mp": 6,
            "race": 0,
            "job": 2,
            "skills": [
                1000,
                4020,
                4021,
                4022
            ]
        },
        {
            "id": 134,
            "name": "시간을 걷는 자 -노아-",
            "tier": 0,
            "cost": 1,
            "hp": 1,
            "mp": 2,
            "race": 0,
            "job": 2,
            "skills": [
                1000,
                4023,
                5007
            ]
        },
        {
            "id": 135,
            "name": "천상의 울림 -벨-",
            "tier": 0,
            "cost": 1,
            "hp": 2,
            "mp": 2,
            "race": 0,
            "job": 2,
            "skills": [
                1000,
                4024
            ]
        },
        {
            "id": 136,
            "name": "망각 -루누스-",
            "tier": 0,
            "cost": 0,
            "hp": 2,
            "mp": 1,
            "race": 0,
            "job": 2,
            "skills": [
                1000,
                5008
            ]
        }
    ]
}